README.md
cdh_ref_python/__init__.py
cdh_ref_python/__main__.py
cdh_ref_python/dbx_accelerator/__init__.py
cdh_ref_python/dbx_accelerator/common/__init__.py
cdh_ref_python/dbx_accelerator/common/cloud.py
cdh_ref_python/dbx_accelerator/common/validator.py
cdh_ref_python/dbx_accelerator/companion.py
cdh_ref_python/dbx_accelerator/dbgems/__init__.py
cdh_ref_python/dbx_accelerator/dbgems/mock_dbutils_class.py
cdh_ref_python/dbx_accelerator/dbgems/mock_spark_context_class.py
cdh_ref_python/dbx_accelerator/sol_acc_util.py
cdh_ref_python/dbx_db_rest/__init__.py
cdh_ref_python/dbx_db_rest/cluster_policies.py
cdh_ref_python/dbx_db_rest/clusters.py
cdh_ref_python/dbx_db_rest/instance_pools.py
cdh_ref_python/dbx_db_rest/jobs.py
cdh_ref_python/dbx_db_rest/ml/__init__.py
cdh_ref_python/dbx_db_rest/ml/feature_store.py
cdh_ref_python/dbx_db_rest/ml/mlflow.py
cdh_ref_python/dbx_db_rest/pipelines.py
cdh_ref_python/dbx_db_rest/repos.py
cdh_ref_python/dbx_db_rest/runs.py
cdh_ref_python/dbx_db_rest/scim/__init__.py
cdh_ref_python/dbx_db_rest/scim/groups.py
cdh_ref_python/dbx_db_rest/scim/service_principals.py
cdh_ref_python/dbx_db_rest/scim/users.py
cdh_ref_python/dbx_db_rest/sql/__init__.py
cdh_ref_python/dbx_db_rest/sql/config.py
cdh_ref_python/dbx_db_rest/sql/endpoints.py
cdh_ref_python/dbx_db_rest/sql/queries.py
cdh_ref_python/dbx_db_rest/tests/__init__.py
cdh_ref_python/dbx_db_rest/tests/all.py
cdh_ref_python/dbx_db_rest/tests/highlevel.py
cdh_ref_python/dbx_db_rest/token_management.py
cdh_ref_python/dbx_db_rest/tokens.py
cdh_ref_python/dbx_db_rest/uc.py
cdh_ref_python/dbx_db_rest/workspace.py
cdh_ref_python/dbx_rest/__init__.py
cdh_ref_python/dbx_rest/common.py
cdh_ref_python/dbx_rest/crud.py
cdh_ref_python/dbx_rest/permissions/__init__.py
cdh_ref_python/dbx_rest/permissions/authorization_tokens.py
cdh_ref_python/dbx_rest/permissions/cluster_policies.py
cdh_ref_python/dbx_rest/permissions/clusters.py
cdh_ref_python/dbx_rest/permissions/crud.py
cdh_ref_python-202402.0.24.dist-info/METADATA
cdh_ref_python-202402.0.24.dist-info/WHEEL
cdh_ref_python-202402.0.24.dist-info/entry_points.txt
cdh_ref_python-202402.0.24.dist-info/RECORD
